server.py
heventure_search_mcp-1.1.1.dist-info/METADATA
heventure_search_mcp-1.1.1.dist-info/WHEEL
heventure_search_mcp-1.1.1.dist-info/entry_points.txt
heventure_search_mcp-1.1.1.dist-info/top_level.txt
heventure_search_mcp-1.1.1.dist-info/RECORD
