Metadata-Version: 2.4
Name: heventure-search-mcp
Version: 1.1.1
Summary: 一个无需API key的网页搜索MCP服务器，支持DuckDuckGo和必应搜索
Home-page: https://github.com/HughesCuit/heventure-search-mcp
Author: HughesCuit
License: MIT
Project-URL: Homepage, https://github.com/HughesCuit/heventure-search-mcp
Project-URL: Repository, https://github.com/HughesCuit/heventure-search-mcp
Project-URL: Issues, https://github.com/HughesCuit/heventure-search-mcp/issues
Project-URL: Documentation, https://github.com/HughesCuit/heventure-search-mcp#readme
Keywords: mcp,search,web,duckduckgo,bing,api
Classifier: Development Status :: 4 - Beta
Classifier: Intended Audience :: Developers
Classifier: License :: OSI Approved :: MIT License
Classifier: Operating System :: OS Independent
Classifier: Programming Language :: Python :: 3
Classifier: Programming Language :: Python :: 3.8
Classifier: Programming Language :: Python :: 3.9
Classifier: Programming Language :: Python :: 3.10
Classifier: Programming Language :: Python :: 3.11
Classifier: Programming Language :: Python :: 3.12
Classifier: Topic :: Internet :: WWW/HTTP :: Indexing/Search
Classifier: Topic :: Software Development :: Libraries :: Python Modules
Requires-Python: >=3.8
Requires-Dist: mcp>=1.0.0
Requires-Dist: aiohttp>=3.8.0
Requires-Dist: beautifulsoup4>=4.11.0
Requires-Dist: lxml>=4.9.0
Requires-Dist: pydantic>=2.0.0
Dynamic: home-page
Dynamic: requires-python
